[
  {
    "title": "Vintage Chadron Hoodie - XL",
    "price": 1200,
    "imageUrl": "/images/products/1_1.webp",
    "isSoldout": true,
    "href": "#",
    "tag": "blusas"
  },
  {
    "title": "Vintage Chadron Hoodie - XL",
    "price": 1200,
    "imageUrl": "/images/products/1_1.webp",
    "isSoldout": true,
    "href": "#",
    "tag": "pantalones"
  },
  {
    "title": "Vintage Chadron Hoodie - XL",
    "price": 1200,
    "imageUrl": "/images/products/1_1.webp",
    "isSoldout": true,
    "href": "#",
    "tag": "camisas"
  },
  {
    "title": "Vintage Chadron Hoodie - XL",
    "price": 1200,
    "imageUrl": "/images/products/1_1.webp",
    "isSoldout": true,
    "href": "#",
    "tag": "vestidos"
  },
  {
    "title": "Vintage Chadron Hoodie - XL",
    "price": 1200,
    "imageUrl": "/images/products/1_1.webp",
    "isSoldout": true,
    "href": "#",
    "tag": "vestidos"
  },
  {
    "title": "Vintage Chadron Hoodie - XL",
    "price": 1200,
    "imageUrl": "/images/products/1_1.webp",
    "isSoldout": true,
    "href": "#",
    "tag": "poleras"
  },
  {
    "title": "Vintage Chadron Hoodie - XL",
    "price": 1200,
    "imageUrl": "/images/products/1_1.webp",
    "isSoldout": true,
    "href": "#",
    "tag": "abrigos"
  },
  {
    "title": "Vintage Chadron Hoodie - XL",
    "price": 1200,
    "imageUrl": "/images/products/1_1.webp",
    "isSoldout": true,
    "href": "#",
    "tag": "blusas"
  }
]
